odoo/addons/attachment_queue/README.rst
odoo/addons/attachment_queue/__init__.py
odoo/addons/attachment_queue/__manifest__.py
odoo/addons/attachment_queue/data/mail_template.xml
odoo/addons/attachment_queue/data/queue_job_channel.xml
odoo/addons/attachment_queue/demo/attachment_queue.xml
odoo/addons/attachment_queue/i18n/attachment_queue.pot
odoo/addons/attachment_queue/i18n/es.po
odoo/addons/attachment_queue/i18n/it.po
odoo/addons/attachment_queue/migrations/18.0.1.0.0/pre-migrate.py
odoo/addons/attachment_queue/models/__init__.py
odoo/addons/attachment_queue/models/attachment_queue.py
odoo/addons/attachment_queue/readme/CONTRIBUTORS.md
odoo/addons/attachment_queue/readme/DESCRIPTION.md
odoo/addons/attachment_queue/readme/USAGE.md
odoo/addons/attachment_queue/security/ir.model.access.csv
odoo/addons/attachment_queue/static/description/form.png
odoo/addons/attachment_queue/static/description/icon.png
odoo/addons/attachment_queue/static/description/index.html
odoo/addons/attachment_queue/static/description/tree.png
odoo/addons/attachment_queue/tests/__init__.py
odoo/addons/attachment_queue/tests/test_attachment_queue.py
odoo/addons/attachment_queue/tests/test_models.py
odoo/addons/attachment_queue/views/attachment_queue_view.xml
odoo/addons/attachment_queue/wizards/__init__.py
odoo/addons/attachment_queue/wizards/attachement_queue_reschedule.py
odoo/addons/attachment_queue/wizards/attachement_queue_reschedule.xml
odoo_addon_attachment_queue-18.0.1.0.0.7.dist-info/METADATA
odoo_addon_attachment_queue-18.0.1.0.0.7.dist-info/WHEEL
odoo_addon_attachment_queue-18.0.1.0.0.7.dist-info/top_level.txt
odoo_addon_attachment_queue-18.0.1.0.0.7.dist-info/RECORD
