Metadata-Version: 2.1
Name: odoo-addon-attachment_queue
Version: 18.0.1.0.0.7
Requires-Python: >=3.10
Requires-Dist: odoo-addon-queue_job==18.0.*
Requires-Dist: odoo==18.0.*
Requires-Dist: openupgradelib
Summary: Base module adding the concept of queue for processing files
Home-page: https://github.com/OCA/server-tools
License: AGPL-3
Author: Akretion,Odoo Community Association (OCA)
Author-email: support@odoo-community.org
Classifier: Programming Language :: Python
Classifier: Framework :: Odoo
Classifier: Framework :: Odoo :: 18.0
Classifier: License :: OSI Approved :: GNU Affero General Public License v3
